combinedform
