Metadata-Version: 1.0
Name: django-combinedforms
Version: 0.1.5
Summary: Compose Django forms
Home-page: https://github.com/leo-the-manic/django-combinedform
Author: UNKNOWN
Author-email: manicleo@gmail.com
License: LGPL3
Platform: UNKNOWN
